Metadata-Version: 2.4
Name: adafruit-circuitpython-neopixel-spi
Version: 1.0.12
Summary: SPI driven CircuitPython driver for neopixels.
Author-email: Adafruit Industries <circuitpython@adafruit.com>
License: MIT
Project-URL: Homepage, https://github.com/adafruit/Adafruit_CircuitPython_NeoPixel_SPI
Keywords: adafruit,blinka,circuitpython,micropython,neopixel_spi,neopixel
Classifier: Intended Audience :: Developers
Classifier: Topic :: Software Development :: Libraries
Classifier: Topic :: Software Development :: Embedded Systems
Classifier: Topic :: System :: Hardware
Classifier: License :: OSI Approved :: MIT License
Classifier: Programming Language :: Python :: 3
License-File: LICENSE
Requires-Dist: Adafruit-Blinka
Requires-Dist: adafruit-circuitpython-busdevice
Requires-Dist: adafruit-circuitpython-pixelbuf
Provides-Extra: optional
Dynamic: license-file
